pypi_bonjour/common_cpp_cmake.cpython-38-x86_64-linux-gnu.so
pypi_bonjour/__init__.py
pypi_bonjour/common.py
pypi_bonjour-0.0.6.dist-info/RECORD
pypi_bonjour-0.0.6.dist-info/WHEEL
pypi_bonjour-0.0.6.dist-info/LICENSE
pypi_bonjour-0.0.6.dist-info/top_level.txt
pypi_bonjour-0.0.6.dist-info/METADATA
